astronomer/__init__.py
astronomer/aeroscope/__init__.py
astronomer/aeroscope/operators.py
astronomer/aeroscope/plugins/__init__.py
astronomer/aeroscope/plugins/templates/formhelper.html
astronomer/aeroscope/plugins/templates/main.html
astronomer/aeroscope/util.py
astronomer_aeroscope-0.9.1.dist-info/entry_points.txt
astronomer_aeroscope-0.9.1.dist-info/WHEEL
astronomer_aeroscope-0.9.1.dist-info/METADATA
astronomer_aeroscope-0.9.1.dist-info/RECORD
