Metadata-Version: 2.1
Name: astronomer-aeroscope
Version: 0.9.1
Summary: An Airflow Plugin and Operator for alternative methods of running Telescope
License: Proprietary
Author: telescope
Author-email: cse@astronomer.io
Requires-Python: >=3
Classifier: License :: Other/Proprietary License
Classifier: Programming Language :: Python :: 3
Classifier: Programming Language :: Python :: 3.4
Classifier: Programming Language :: Python :: 3.5
Classifier: Programming Language :: Python :: 3.6
Classifier: Programming Language :: Python :: 3.7
Classifier: Programming Language :: Python :: 3.8
Classifier: Programming Language :: Python :: 3.9
Classifier: Programming Language :: Python :: 3.10
